odoo/addons/ssi_fixed_asset_complex_asset/README.rst
odoo/addons/ssi_fixed_asset_complex_asset/__init__.py
odoo/addons/ssi_fixed_asset_complex_asset/__manifest__.py
odoo/addons/ssi_fixed_asset_complex_asset/data/approval_template_data.xml
odoo/addons/ssi_fixed_asset_complex_asset/data/ir_sequence_data.xml
odoo/addons/ssi_fixed_asset_complex_asset/data/policy_template_data.xml
odoo/addons/ssi_fixed_asset_complex_asset/data/sequence_template_data.xml
odoo/addons/ssi_fixed_asset_complex_asset/i18n/id.po
odoo/addons/ssi_fixed_asset_complex_asset/i18n/ssi_fixed_asset_complex_asset.pot
odoo/addons/ssi_fixed_asset_complex_asset/models/__init__.py
odoo/addons/ssi_fixed_asset_complex_asset/models/complex_fixed_asset_installation.py
odoo/addons/ssi_fixed_asset_complex_asset/models/complex_fixed_asset_removal.py
odoo/addons/ssi_fixed_asset_complex_asset/security/ir.model.access.csv
odoo/addons/ssi_fixed_asset_complex_asset/security/ir_module_category_data.xml
odoo/addons/ssi_fixed_asset_complex_asset/security/ir_rule_data.xml
odoo/addons/ssi_fixed_asset_complex_asset/security/res_group_data.xml
odoo/addons/ssi_fixed_asset_complex_asset/static/description/banner.png
odoo/addons/ssi_fixed_asset_complex_asset/static/description/icon.png
odoo/addons/ssi_fixed_asset_complex_asset/views/complex_fixed_asset_installation_views.xml
odoo/addons/ssi_fixed_asset_complex_asset/views/complex_fixed_asset_removal_views.xml
odoo14_addon_ssi_fixed_asset_complex_asset-14.0.1.2.0.dist-info/METADATA
odoo14_addon_ssi_fixed_asset_complex_asset-14.0.1.2.0.dist-info/WHEEL
odoo14_addon_ssi_fixed_asset_complex_asset-14.0.1.2.0.dist-info/top_level.txt
odoo14_addon_ssi_fixed_asset_complex_asset-14.0.1.2.0.dist-info/RECORD
